fog2d/__init__.py
fog2d/collision.py
fog2d/engine.py
fog2d/entity.py
fog2d/input.py
fog2d/lighting.py
fog2d/renderer.py
fog2d/scene.py
fog2d/utils.py
fog2d-0.1.3.dist-info/METADATA
fog2d-0.1.3.dist-info/WHEEL
fog2d-0.1.3.dist-info/top_level.txt
fog2d-0.1.3.dist-info/RECORD
