Metadata-Version: 2.4
Name: fog2d
Version: 0.1.3
Summary: Fog2D – Console 2D Engine with pseudo-graphics, lighting and collision
Author: XDevster
License: BSD 3-Clause License
Requires-Dist: colorama
